README.md
setup.py
async_cached.egg-info/PKG-INFO
async_cached.egg-info/SOURCES.txt
async_cached.egg-info/dependency_links.txt
async_cached.egg-info/top_level.txt
asynccached/__init__.py
asynccached/asynccached.py