Metadata-Version: 2.1
Name: async-cached
Version: 3.11.2
Summary: Decorator to cache async function results
Home-page: https://github.com/aiocoro/async-cached
Author: aiocoro
Author-email: aiocoro@protonmail.ch
License: UNKNOWN
Platform: UNKNOWN
Classifier: License :: OSI Approved :: MIT License
Classifier: Operating System :: OS Independent
Classifier: Programming Language :: Python :: 3
